pyrsm/__init__.py
pyrsm/bins.py
pyrsm/notebook.py
pyrsm/plot_utils.py
pyrsm/props.py
pyrsm/stats.py
pyrsm/utils.py
pyrsm/basics/__init__.py
pyrsm/basics/central_limit_theorem.py
pyrsm/basics/compare_means.py
pyrsm/basics/compare_props.py
pyrsm/basics/correlation.py
pyrsm/basics/cross_tabs.py
pyrsm/basics/display_utils.py
pyrsm/basics/goodness.py
pyrsm/basics/plotting_utils.py
pyrsm/basics/probability_calculator.py
pyrsm/basics/single_mean.py
pyrsm/basics/single_prop.py
pyrsm/basics/utils.py
pyrsm/basics/prob_calc/__init__.py
pyrsm/basics/prob_calc/binomial.py
pyrsm/basics/prob_calc/chisq.py
pyrsm/basics/prob_calc/discrete.py
pyrsm/basics/prob_calc/exponential.py
pyrsm/basics/prob_calc/fdist.py
pyrsm/basics/prob_calc/lnorm.py
pyrsm/basics/prob_calc/normal.py
pyrsm/basics/prob_calc/poisson.py
pyrsm/basics/prob_calc/tdist.py
pyrsm/basics/prob_calc/uniform.py
pyrsm/basics/prob_calc/utils.py
pyrsm/design/__init__.py
pyrsm/design/sample_size.py
pyrsm/eda/__init__.py
pyrsm/eda/combine.py
pyrsm/eda/distr.py
pyrsm/eda/explore.py
pyrsm/eda/pivot.py
pyrsm/eda/unpivot.py
pyrsm/eda/visualize.py
pyrsm/model/__init__.py
pyrsm/model/logistic.py
pyrsm/model/mlp.py
pyrsm/model/model.py
pyrsm/model/perf.py
pyrsm/model/regress.py
pyrsm/model/rforest.py
pyrsm/model/visualize.py
pyrsm/model/xgboost.py
pyrsm/multivariate/__init__.py
pyrsm/multivariate/factor.py
pyrsm-2.2.0.dist-info/licenses/LICENSE
pyrsm-2.2.0.dist-info/METADATA
pyrsm-2.2.0.dist-info/WHEEL
pyrsm-2.2.0.dist-info/top_level.txt
pyrsm-2.2.0.dist-info/RECORD
